Workbook

Sheet 01_Corrupted_General_Ledger
A1: Txn_ID | B1: Posting_Date | C1: GL_Account | D1: Vendor_ID | E1: Quantity_Units | F1: Unit_Price_USD | G1: Raw_Extended_Cost | H1: Target_Subledger_Balance
A2: TXN-1001 | B2: 46023 | C2: 6001-OPEX | D2: VEND-801 | E2: 150 | F2: 45 | G2: 6750 | H2: 6750
A3: TXN-1002 | B3: 46023 | C3: 6002-CAPEX | D3: VEND-999 | E3: 80 | F3: #N/A | G3: #N/A | H3: 3200
A4: TXN-1003 | B4: 46024 | C4: 6001-OPEX | D4: VEND-803 | E4: 0 | F4: 120 | G4: #DIV/0! | H4: 0
A5: TXN-1004 | B5: 46024 | C5: 6003-SUPPLY | D5: VEND-804 | E5: 200 | F5: $15.50 | G5: 3100 | H5: 3100
A6: TXN-1005 | B6: 46025 | C6: 6001-OPEX | D6: VEND-805 | E6: 50 | F6: 310 | G6: 15500 | H6: 15500
A7: TXN-1006 | B7: 46025 | C7: 6004-TRAVEL | D7: VEND-806 | E7: INVALID_QTY | F7: 75 | G7: #VALUE! | H7: 1875
A8: TXN-1007 | B8: 46026 | C8: 6002-CAPEX | D8: VEND-807 | E8: 120 | F8: 95 | G8: 11400 | H8: 11400
A9: TXN-1008 | B9: 46026 | C9: 6003-SUPPLY | D9: VEND-808 | E9: 300 | F9: 0 | G9: #DIV/0! | H9: 0
A10: TXN-1009 | B10: 46027 | C10: 6001-OPEX | D10: VEND-999 | E10: 45 | F10: #N/A | G10: #N/A | H10: 1800
A11: TXN-1010 | B11: 46027 | C11: 6004-TRAVEL | D11: VEND-810 | E11: 500 | F11: 12.5 | G11: 6250 | H11: 6250
A12: TXN-1011 | B12: 46028 | C12: 6002-CAPEX | D12: VEND-811 | E12: 175 | F12: $88.00 | G12: 15400 | H12: 15400
A13: TXN-1012 | B13: 46028 | C13: 6001-OPEX | D13: VEND-812 | E13: 0 | F13: 210 | G13: #DIV/0! | H13: 0
A14: TXN-1013 | B14: 46029 | C14: 6003-SUPPLY | D14: VEND-813 | E14: 90 | F14: 140 | G14: 12600 | H14: 12600
A15: TXN-1014 | B15: 46029 | C15: 6001-OPEX | D15: VEND-814 | E15: 220 | F15: 35 | G15: 7700 | H15: 7700
A16: TXN-1015 | B16: 46030 | C16: 6004-TRAVEL | D16: VEND-999 | E16: 110 | F16: #N/A | G16: #N/A | H16: 5500
A17: TXN-1016 | B17: 46030 | C17: 6002-CAPEX | D17: VEND-816 | E17: PENDING_QTY | F17: 62 | G17: #VALUE! | H17: 3100
A18: TXN-1017 | B18: 46031 | C18: 6003-SUPPLY | D18: VEND-817 | E18: 400 | F18: 18 | G18: 7200 | H18: 7200
A19: TXN-1018 | B19: 46031 | C19: 6001-OPEX | D19: VEND-818 | E19: 60 | F19: 450 | G19: 27000 | H19: 27000
A20: TXN-1019 | B20: 46032 | C20: 6004-TRAVEL | D20: VEND-819 | E20: 0 | F20: 175 | G20: #DIV/0! | H20: 0
A21: TXN-1020 | B21: 46032 | C21: 6002-CAPEX | D21: VEND-820 | E21: 130 | F21: $52.00 | G21: 6760 | H21: 6760
A22: TXN-1021 | B22: 46033 | C22: 6003-SUPPLY | D22: VEND-821 | E22: 250 | F22: 24 | G22: 6000 | H22: 6000
A23: TXN-1022 | B23: 46033 | C23: 6001-OPEX | D23: VEND-999 | E23: 95 | F23: #N/A | G23: #N/A | H23: 4750
A24: TXN-1023 | B24: 46034 | C24: 6004-TRAVEL | D24: VEND-823 | E24: 310 | F24: 40 | G24: 12400 | H24: 12400
A25: TXN-1024 | B25: 46034 | C25: 6002-CAPEX | D25: VEND-824 | E25: ERR_FORMAT | F25: 115 | G25: #VALUE! | H25: 5750
A26: TXN-1025 | B26: 46035 | C26: 6003-SUPPLY | D26: VEND-825 | E26: 180 | F26: 85 | G26: 15300 | H26: 15300
A27: TXN-1026 | B27: 46035 | C27: 6001-OPEX | D27: VEND-826 | E27: 140 | F27: 55 | G27: 7700 | H27: 7700
A28: TXN-1027 | B28: 46036 | C28: 6002-CAPEX | D28: VEND-999 | E28: 65 | F28: #N/A | G28: #N/A | H28: 2600
A29: TXN-1028 | B29: 46036 | C29: 6001-OPEX | D29: VEND-828 | E29: 0 | F29: 145 | G29: #DIV/0! | H29: 0
A30: TXN-1029 | B30: 46037 | C30: 6003-SUPPLY | D30: VEND-829 | E30: 210 | F30: $18.50 | G30: 3885 | H30: 3885
A31: TXN-1030 | B31: 46037 | C31: 6001-OPEX | D31: VEND-830 | E31: 45 | F31: 290 | G31: 13050 | H31: 13050
A32: TXN-1031 | B32: 46038 | C32: 6004-TRAVEL | D32: VEND-831 | E32: BAD_DATA | F32: 80 | G32: #VALUE! | H32: 2000
A33: TXN-1032 | B33: 46038 | C33: 6002-CAPEX | D33: VEND-832 | E33: 110 | F33: 105 | G33: 11550 | H33: 11550
A34: TXN-1033 | B34: 46039 | C34: 6003-SUPPLY | D34: VEND-833 | E34: 280 | F34: 0 | G34: #DIV/0! | H34: 0
A35: TXN-1034 | B35: 46039 | C35: 6001-OPEX | D35: VEND-999 | E35: 50 | F35: #N/A | G35: #N/A | H35: 2250
A36: TXN-1035 | B36: 46040 | C36: 6004-TRAVEL | D36: VEND-835 | E36: 450 | F36: 15 | G36: 6750 | H36: 6750
A37: TXN-1036 | B37: 46040 | C37: 6002-CAPEX | D37: VEND-836 | E37: 160 | F37: $92.00 | G37: 14720 | H37: 14720
A38: TXN-1037 | B38: 46041 | C38: 6001-OPEX | D38: VEND-837 | E38: 0 | F38: 230 | G38: #DIV/0! | H38: 0
A39: TXN-1038 | B39: 46041 | C39: 6003-SUPPLY | D39: VEND-838 | E39: 85 | F39: 155 | G39: 13175 | H39: 13175
A40: TXN-1039 | B40: 46042 | C40: 6001-OPEX | D40: VEND-839 | E40: 230 | F40: 42 | G40: 9660 | H40: 9660
A41: TXN-1040 | B41: 46042 | C41: 6004-TRAVEL | D41: VEND-999 | E41: 100 | F41: #N/A | G41: #N/A | H41: 5000
A42: TXN-1041 | B42: 46043 | C42: 6002-CAPEX | D42: VEND-841 | E42: UNCERTAIN | F42: 68 | G42: #VALUE! | H42: 3400
A43: TXN-1042 | B43: 46043 | C43: 6003-SUPPLY | D43: VEND-842 | E43: 380 | F43: 22 | G43: 8360 | H43: 8360
A44: TXN-1043 | B44: 46044 | C44: 6001-OPEX | D44: VEND-843 | E44: 55 | F44: 480 | G44: 26400 | H44: 26400
A45: TXN-1044 | B45: 46044 | C45: 6004-TRAVEL | D45: VEND-844 | E45: 0 | F45: 190 | G45: #DIV/0! | H45: 0
A46: TXN-1045 | B46: 46045 | C46: 6002-CAPEX | D46: VEND-845 | E46: 125 | F46: $60.00 | G46: 7500 | H46: 7500
A47: TXN-1046 | B47: 46045 | C47: 6003-SUPPLY | D47: VEND-846 | E47: 240 | F47: 28 | G47: 6720 | H47: 6720
A48: TXN-1047 | B48: 46046 | C48: 6001-OPEX | D48: VEND-999 | E48: 90 | F48: #N/A | G48: #N/A | H48: 4500
A49: TXN-1048 | B49: 46046 | C49: 6004-TRAVEL | D49: VEND-848 | E49: 300 | F49: 48 | G49: 14400 | H49: 14400
A50: TXN-1049 | B50: 46047 | C50: 6002-CAPEX | D50: VEND-849 | E50: ERR_QTY | F50: 120 | G50: #VALUE! | H50: 6000
A51: TXN-1050 | B51: 46047 | C51: 6003-SUPPLY | D51: VEND-850 | E51: 170 | F51: 90 | G51: 15300 | H51: 15300
A52: TXN-1051 | B52: 46048 | C52: 6001-OPEX | D52: VEND-851 | E52: 130 | F52: 48 | G52: 6240 | H52: 6240
A53: TXN-1052 | B53: 46048 | C53: 6002-CAPEX | D53: VEND-999 | E53: 75 | F53: #N/A | G53: #N/A | H53: 3000
A54: TXN-1053 | B54: 46049 | C54: 6001-OPEX | D54: VEND-853 | E54: 0 | F54: 110 | G54: #DIV/0! | H54: 0
A55: TXN-1054 | B55: 46049 | C55: 6003-SUPPLY | D55: VEND-854 | E55: 190 | F55: $16.00 | G55: 3040 | H55: 3040
A56: TXN-1055 | B56: 46050 | C56: 6001-OPEX | D56: VEND-855 | E56: 60 | F56: 320 | G56: 19200 | H56: 19200
A57: TXN-1056 | B57: 46050 | C57: 6004-TRAVEL | D57: VEND-856 | E57: INVALID_INPUT | F57: 70 | G57: #VALUE! | H57: 1750
A58: TXN-1057 | B58: 46051 | C58: 6002-CAPEX | D58: VEND-857 | E58: 100 | F58: 85 | G58: 8500 | H58: 8500
A59: TXN-1058 | B59: 46051 | C59: 6003-SUPPLY | D59: VEND-858 | E59: 260 | F59: 0 | G59: #DIV/0! | H59: 0
A60: TXN-1059 | B60: 46052 | C60: 6001-OPEX | D60: VEND-999 | E60: 40 | F60: #N/A | G60: #N/A | H60: 1600
A61: TXN-1060 | B61: 46052 | C61: 6004-TRAVEL | D61: VEND-860 | E61: 420 | F61: 11.5 | G61: 4830 | H61: 4830
A62: TXN-1061 | B62: 46053 | C62: 6002-CAPEX | D62: VEND-861 | E62: 150 | F62: $95.00 | G62: 14250 | H62: 14250
A63: TXN-1062 | B63: 46053 | C63: 6001-OPEX | D63: VEND-862 | E63: 0 | F63: 200 | G63: #DIV/0! | H63: 0
A64: TXN-1063 | B64: 46054 | C64: 6003-SUPPLY | D64: VEND-863 | E64: 80 | F64: 135 | G64: 10800 | H64: 10800
A65: TXN-1064 | B65: 46054 | C65: 6001-OPEX | D65: VEND-864 | E65: 210 | F65: 32 | G65: 6720 | H65: 6720
A66: TXN-1065 | B66: 46055 | C66: 6004-TRAVEL | D66: VEND-999 | E66: 105 | F66: #N/A | G66: #N/A | H66: 5250
A67: TXN-1066 | B67: 46055 | C67: 6002-CAPEX | D67: VEND-866 | E67: MISSING | F67: 65 | G67: #VALUE! | H67: 3250
A68: TXN-1067 | B68: 46056 | C68: 6003-SUPPLY | D68: VEND-867 | E68: 390 | F68: 19 | G68: 7410 | H68: 7410
A69: TXN-1068 | B69: 46056 | C69: 6001-OPEX | D69: VEND-868 | E69: 50 | F69: 420 | G69: 21000 | H69: 21000
A70: TXN-1069 | B70: 46057 | C70: 6004-TRAVEL | D70: VEND-869 | E70: 0 | F70: 165 | G70: #DIV/0! | H70: 0
A71: TXN-1070 | B71: 46057 | C71: 6002-CAPEX | D71: VEND-870 | E71: 115 | F71: $58.00 | G71: 6670 | H71: 6670
A72: TXN-1071 | B72: 46058 | C72: 6003-SUPPLY | D72: VEND-871 | E72: 230 | F72: 26 | G72: 5980 | H72: 5980
A73: TXN-1072 | B73: 46058 | C73: 6001-OPEX | D73: VEND-999 | E73: 85 | F73: #N/A | G73: #N/A | H73: 4250
A74: TXN-1073 | B74: 46059 | C74: 6004-TRAVEL | D74: VEND-873 | E74: 290 | F74: 44 | G74: 12760 | H74: 12760
A75: TXN-1074 | B75: 46059 | C75: 6002-CAPEX | D75: VEND-874 | E75: NOT_AVAIL | F75: 110 | G75: #VALUE! | H75: 5500
A76: TXN-1075 | B76: 46060 | C76: 6003-SUPPLY | D76: VEND-875 | E76: 160 | F76: 82 | G76: 13120 | H76: 13120
A77: TXN-1076 | B77: 46060 | C77: 6001-OPEX | D77: VEND-876 | E77: 125 | F77: 52 | G77: 6500 | H77: 6500
A78: TXN-1077 | B78: 46061 | C78: 6002-CAPEX | D78: VEND-999 | E78: 70 | F78: #N/A | G78: #N/A | H78: 2800
A79: TXN-1078 | B79: 46061 | C79: 6001-OPEX | D79: VEND-878 | E79: 0 | F79: 130 | G79: #DIV/0! | H79: 0
A80: TXN-1079 | B80: 46062 | C80: 6003-SUPPLY | D80: VEND-879 | E80: 200 | F80: $17.50 | G80: 3500 | H80: 3500
A81: TXN-1080 | B81: 46062 | C81: 6001-OPEX | D81: VEND-880 | E81: 50 | F81: 300 | G81: 15000 | H81: 15000
A82: TXN-1081 | B82: 46063 | C82: 6004-TRAVEL | D82: VEND-881 | E82: TEXT_ERR | F82: 75 | G82: #VALUE! | H82: 1875
A83: TXN-1082 | B83: 46063 | C83: 6002-CAPEX | D83: VEND-882 | E83: 105 | F83: 98 | G83: 10290 | H83: 10290
A84: TXN-1083 | B84: 46064 | C84: 6003-SUPPLY | D84: VEND-883 | E84: 270 | F84: 0 | G84: #DIV/0! | H84: 0
A85: TXN-1084 | B85: 46064 | C85: 6001-OPEX | D85: VEND-999 | E85: 45 | F85: #N/A | G85: #N/A | H85: 2025
A86: TXN-1085 | B86: 46065 | C86: 6004-TRAVEL | D86: VEND-885 | E86: 440 | F86: 14 | G86: 6160 | H86: 6160
A87: TXN-1086 | B87: 46065 | C87: 6002-CAPEX | D87: VEND-886 | E87: 155 | F87: $90.00 | G87: 13950 | H87: 13950
A88: TXN-1087 | B88: 46066 | C88: 6001-OPEX | D88: VEND-887 | E88: 0 | F88: 220 | G88: #DIV/0! | H88: 0
A89: TXN-1088 | B89: 46066 | C89: 6003-SUPPLY | D89: VEND-888 | E89: 80 | F89: 148 | G89: 11840 | H89: 11840
A90: TXN-1089 | B90: 46067 | C90: 6001-OPEX | D90: VEND-889 | E90: 220 | F90: 40 | G90: 8800 | H90: 8800
A91: TXN-1090 | B91: 46067 | C91: 6004-TRAVEL | D91: VEND-999 | E91: 95 | F91: #N/A | G91: #N/A | H91: 4750
A92: TXN-1091 | B92: 46068 | C92: 6002-CAPEX | D92: VEND-891 | E92: UNPARSED | F92: 64 | G92: #VALUE! | H92: 3200
A93: TXN-1092 | B93: 46068 | C93: 6003-SUPPLY | D93: VEND-892 | E93: 370 | F93: 20 | G93: 7400 | H93: 7400
A94: TXN-1093 | B94: 46069 | C94: 6001-OPEX | D94: VEND-893 | E94: 50 | F94: 460 | G94: 23000 | H94: 23000
A95: TXN-1094 | B95: 46069 | C95: 6004-TRAVEL | D95: VEND-894 | E95: 0 | F95: 180 | G95: #DIV/0! | H95: 0
A96: TXN-1095 | B96: 46070 | C96: 6002-CAPEX | D96: VEND-895 | E96: 120 | F96: $64.00 | G96: 7680 | H96: 7680
A97: TXN-1096 | B97: 46070 | C97: 6003-SUPPLY | D97: VEND-896 | E97: 235 | F97: 30 | G97: 7050 | H97: 7050
A98: TXN-1097 | B98: 46071 | C98: 6001-OPEX | D98: VEND-999 | E98: 88 | F98: #N/A | G98: #N/A | H98: 4400
A99: TXN-1098 | B99: 46071 | C99: 6004-TRAVEL | D99: VEND-898 | E99: 295 | F99: 46 | G99: 13570 | H99: 13570
A100: TXN-1099 | B100: 46072 | C100: 6002-CAPEX | D100: VEND-899 | E100: NON_NUMERIC | F100: 125 | G100: #VALUE! | H100: 6250
...

Sheet 02_Formula_Repair_Engine
A1: Txn_ID | B1: Posting_Date | C1: GL_Account | D1: Repaired_Vendor_ID | E1: Clean_Quantity_Units | F1: Clean_Unit_Price_USD | G1: Repaired_Extended_Cost | H1: Audit_Status
A2: ='01_Corrupted_General_Ledger'!A2 -> TXN-1001 | B2: ='01_Corrupted_General_Ledger'!B2 -> 46023 | C2: ='01_Corrupted_General_Ledger'!C2 -> 6001-OPEX | D2: =IF(OR('01_Corrupted_General_Ledger'!D2="VEND-999", '01_Corrupted_General_Ledger'!D2="#N/A", ISBLANK('01_Corrupted_General_Ledger'!D2)), "VEND-DEFAULT", '01_Corrupted_General_Ledger'!D2) -> VEND-801 | E2: =IFERROR(VALUE(TRIM('01_Corrupted_General_Ledger'!E2)), 1) -> 150 | F2: =IFERROR(VALUE(TRIM(SUBSTITUTE(SUBSTITUTE('01_Corrupted_General_Ledger'!F2, "$", ""), " ", ""))), 0) -> 45 | G2: =E2*F2 -> 6750 | H2: =IF(OR(ISERROR('01_Corrupted_General_Ledger'!G2), '01_Corrupted_General_Ledger'!D2="VEND-999"), "REPAIRED", "VERIFIED CLEAN") -> VERIFIED CLEAN
A3: ='01_Corrupted_General_Ledger'!A3 -> TXN-1002 | B3: ='01_Corrupted_General_Ledger'!B3 -> 46023 | C3: ='01_Corrupted_General_Ledger'!C3 -> 6002-CAPEX | D3: =IF(OR('01_Corrupted_General_Ledger'!D3="VEND-999", '01_Corrupted_General_Ledger'!D3="#N/A", ISBLANK('01_Corrupted_General_Ledger'!D3)), "VEND-DEFAULT", '01_Corrupted_General_Ledger'!D3) -> VEND-DEFAULT | E3: =IFERROR(VALUE(TRIM('01_Corrupted_General_Ledger'!E3)), 1) -> 80 | F3: =IFERROR(VALUE(TRIM(SUBSTITUTE(SUBSTITUTE('01_Corrupted_General_Ledger'!F3, "$", ""), " ", ""))), 0) -> 0 | G3: =E3*F3 -> 0 | H3: =IF(OR(ISERROR('01_Corrupted_General_Ledger'!G3), '01_Corrupted_General_Ledger'!D3="VEND-999"), "REPAIRED", "VERIFIED CLEAN") -> REPAIRED
A4: ='01_Corrupted_General_Ledger'!A4 -> TXN-1003 | B4: ='01_Corrupted_General_Ledger'!B4 -> 46024 | C4: ='01_Corrupted_General_Ledger'!C4 -> 6001-OPEX | D4: =IF(OR('01_Corrupted_General_Ledger'!D4="VEND-999", '01_Corrupted_General_Ledger'!D4="#N/A", ISBLANK('01_Corrupted_General_Ledger'!D4)), "VEND-DEFAULT", '01_Corrupted_General_Ledger'!D4) -> VEND-803 | E4: =IFERROR(VALUE(TRIM('01_Corrupted_General_Ledger'!E4)), 1) -> 0 | F4: =IFERROR(VALUE(TRIM(SUBSTITUTE(SUBSTITUTE('01_Corrupted_General_Ledger'!F4, "$", ""), " ", ""))), 0) -> 120 | G4: =E4*F4 -> 0 | H4: =IF(OR(ISERROR('01_Corrupted_General_Ledger'!G4), '01_Corrupted_General_Ledger'!D4="VEND-999"), "REPAIRED", "VERIFIED CLEAN") -> REPAIRED
A5: ='01_Corrupted_General_Ledger'!A5 -> TXN-1004 | B5: ='01_Corrupted_General_Ledger'!B5 -> 46024 | C5: ='01_Corrupted_General_Ledger'!C5 -> 6003-SUPPLY | D5: =IF(OR('01_Corrupted_General_Ledger'!D5="VEND-999", '01_Corrupted_General_Ledger'!D5="#N/A", ISBLANK('01_Corrupted_General_Ledger'!D5)), "VEND-DEFAULT", '01_Corrupted_General_Ledger'!D5) -> VEND-804 | E5: =IFERROR(VALUE(TRIM('01_Corrupted_General_Ledger'!E5)), 1) -> 200 | F5: =IFERROR(VALUE(TRIM(SUBSTITUTE(SUBSTITUTE('01_Corrupted_General_Ledger'!F5, "$", ""), " ", ""))), 0) -> 15.5 | G5: =E5*F5 -> 3100 | H5: =IF(OR(ISERROR('01_Corrupted_General_Ledger'!G5), '01_Corrupted_General_Ledger'!D5="VEND-999"), "REPAIRED", "VERIFIED CLEAN") -> VERIFIED CLEAN
A6: ='01_Corrupted_General_Ledger'!A6 -> TXN-1005 | B6: ='01_Corrupted_General_Ledger'!B6 -> 46025 | C6: ='01_Corrupted_General_Ledger'!C6 -> 6001-OPEX | D6: =IF(OR('01_Corrupted_General_Ledger'!D6="VEND-999", '01_Corrupted_General_Ledger'!D6="#N/A", ISBLANK('01_Corrupted_General_Ledger'!D6)), "VEND-DEFAULT", '01_Corrupted_General_Ledger'!D6) -> VEND-805 | E6: =IFERROR(VALUE(TRIM('01_Corrupted_General_Ledger'!E6)), 1) -> 50 | F6: =IFERROR(VALUE(TRIM(SUBSTITUTE(SUBSTITUTE('01_Corrupted_General_Ledger'!F6, "$", ""), " ", ""))), 0) -> 310 | G6: =E6*F6 -> 15500 | H6: =IF(OR(ISERROR('01_Corrupted_General_Ledger'!G6), '01_Corrupted_General_Ledger'!D6="VEND-999"), "REPAIRED", "VERIFIED CLEAN") -> VERIFIED CLEAN
A7: ='01_Corrupted_General_Ledger'!A7 -> TXN-1006 | B7: ='01_Corrupted_General_Ledger'!B7 -> 46025 | C7: ='01_Corrupted_General_Ledger'!C7 -> 6004-TRAVEL | D7: =IF(OR('01_Corrupted_General_Ledger'!D7="VEND-999", '01_Corrupted_General_Ledger'!D7="#N/A", ISBLANK('01_Corrupted_General_Ledger'!D7)), "VEND-DEFAULT", '01_Corrupted_General_Ledger'!D7) -> VEND-806 | E7: =IFERROR(VALUE(TRIM('01_Corrupted_General_Ledger'!E7)), 1) -> 1 | F7: =IFERROR(VALUE(TRIM(SUBSTITUTE(SUBSTITUTE('01_Corrupted_General_Ledger'!F7, "$", ""), " ", ""))), 0) -> 75 | G7: =E7*F7 -> 75 | H7: =IF(OR(ISERROR('01_Corrupted_General_Ledger'!G7), '01_Corrupted_General_Ledger'!D7="VEND-999"), "REPAIRED", "VERIFIED CLEAN") -> REPAIRED
A8: ='01_Corrupted_General_Ledger'!A8 -> TXN-1007 | B8: ='01_Corrupted_General_Ledger'!B8 -> 46026 | C8: ='01_Corrupted_General_Ledger'!C8 -> 6002-CAPEX | D8: =IF(OR('01_Corrupted_General_Ledger'!D8="VEND-999", '01_Corrupted_General_Ledger'!D8="#N/A", ISBLANK('01_Corrupted_General_Ledger'!D8)), "VEND-DEFAULT", '01_Corrupted_General_Ledger'!D8) -> VEND-807 | E8: =IFERROR(VALUE(TRIM('01_Corrupted_General_Ledger'!E8)), 1) -> 120 | F8: =IFERROR(VALUE(TRIM(SUBSTITUTE(SUBSTITUTE('01_Corrupted_General_Ledger'!F8, "$", ""), " ", ""))), 0) -> 95 | G8: =E8*F8 -> 11400 | H8: =IF(OR(ISERROR('01_Corrupted_General_Ledger'!G8), '01_Corrupted_General_Ledger'!D8="VEND-999"), "REPAIRED", "VERIFIED CLEAN") -> VERIFIED CLEAN
A9: ='01_Corrupted_General_Ledger'!A9 -> TXN-1008 | B9: ='01_Corrupted_General_Ledger'!B9 -> 46026 | C9: ='01_Corrupted_General_Ledger'!C9 -> 6003-SUPPLY | D9: =IF(OR('01_Corrupted_General_Ledger'!D9="VEND-999", '01_Corrupted_General_Ledger'!D9="#N/A", ISBLANK('01_Corrupted_General_Ledger'!D9)), "VEND-DEFAULT", '01_Corrupted_General_Ledger'!D9) -> VEND-808 | E9: =IFERROR(VALUE(TRIM('01_Corrupted_General_Ledger'!E9)), 1) -> 300 | F9: =IFERROR(VALUE(TRIM(SUBSTITUTE(SUBSTITUTE('01_Corrupted_General_Ledger'!F9, "$", ""), " ", ""))), 0) -> 0 | G9: =E9*F9 -> 0 | H9: =IF(OR(ISERROR('01_Corrupted_General_Ledger'!G9), '01_Corrupted_General_Ledger'!D9="VEND-999"), "REPAIRED", "VERIFIED CLEAN") -> REPAIRED
A10: ='01_Corrupted_General_Ledger'!A10 -> TXN-1009 | B10: ='01_Corrupted_General_Ledger'!B10 -> 46027 | C10: ='01_Corrupted_General_Ledger'!C10 -> 6001-OPEX | D10: =IF(OR('01_Corrupted_General_Ledger'!D10="VEND-999", '01_Corrupted_General_Ledger'!D10="#N/A", ISBLANK('01_Corrupted_General_Ledger'!D10)), "VEND-DEFAULT", '01_Corrupted_General_Ledger'!D10) -> VEND-DEFAULT | E10: =IFERROR(VALUE(TRIM('01_Corrupted_General_Ledger'!E10)), 1) -> 45 | F10: =IFERROR(VALUE(TRIM(SUBSTITUTE(SUBSTITUTE('01_Corrupted_General_Ledger'!F10, "$", ""), " ", ""))), 0) -> 0 | G10: =E10*F10 -> 0 | H10: =IF(OR(ISERROR('01_Corrupted_General_Ledger'!G10), '01_Corrupted_General_Ledger'!D10="VEND-999"), "REPAIRED", "VERIFIED CLEAN") -> REPAIRED
A11: ='01_Corrupted_General_Ledger'!A11 -> TXN-1010 | B11: ='01_Corrupted_General_Ledger'!B11 -> 46027 | C11: ='01_Corrupted_General_Ledger'!C11 -> 6004-TRAVEL | D11: =IF(OR('01_Corrupted_General_Ledger'!D11="VEND-999", '01_Corrupted_General_Ledger'!D11="#N/A", ISBLANK('01_Corrupted_General_Ledger'!D11)), "VEND-DEFAULT", '01_Corrupted_General_Ledger'!D11) -> VEND-810 | E11: =IFERROR(VALUE(TRIM('01_Corrupted_General_Ledger'!E11)), 1) -> 500 | F11: =IFERROR(VALUE(TRIM(SUBSTITUTE(SUBSTITUTE('01_Corrupted_General_Ledger'!F11, "$", ""), " ", ""))), 0) -> 12.5 | G11: =E11*F11 -> 6250 | H11: =IF(OR(ISERROR('01_Corrupted_General_Ledger'!G11), '01_Corrupted_General_Ledger'!D11="VEND-999"), "REPAIRED", "VERIFIED CLEAN") -> VERIFIED CLEAN
A12: ='01_Corrupted_General_Ledger'!A12 -> TXN-1011 | B12: ='01_Corrupted_General_Ledger'!B12 -> 46028 | C12: ='01_Corrupted_General_Ledger'!C12 -> 6002-CAPEX | D12: =IF(OR('01_Corrupted_General_Ledger'!D12="VEND-999", '01_Corrupted_General_Ledger'!D12="#N/A", ISBLANK('01_Corrupted_General_Ledger'!D12)), "VEND-DEFAULT", '01_Corrupted_General_Ledger'!D12) -> VEND-811 | E12: =IFERROR(VALUE(TRIM('01_Corrupted_General_Ledger'!E12)), 1) -> 175 | F12: =IFERROR(VALUE(TRIM(SUBSTITUTE(SUBSTITUTE('01_Corrupted_General_Ledger'!F12, "$", ""), " ", ""))), 0) -> 88 | G12: =E12*F12 -> 15400 | H12: =IF(OR(ISERROR('01_Corrupted_General_Ledger'!G12), '01_Corrupted_General_Ledger'!D12="VEND-999"), "REPAIRED", "VERIFIED CLEAN") -> VERIFIED CLEAN
A13: ='01_Corrupted_General_Ledger'!A13 -> TXN-1012 | B13: ='01_Corrupted_General_Ledger'!B13 -> 46028 | C13: ='01_Corrupted_General_Ledger'!C13 -> 6001-OPEX | D13: =IF(OR('01_Corrupted_General_Ledger'!D13="VEND-999", '01_Corrupted_General_Ledger'!D13="#N/A", ISBLANK('01_Corrupted_General_Ledger'!D13)), "VEND-DEFAULT", '01_Corrupted_General_Ledger'!D13) -> VEND-812 | E13: =IFERROR(VALUE(TRIM('01_Corrupted_General_Ledger'!E13)), 1) -> 0 | F13: =IFERROR(VALUE(TRIM(SUBSTITUTE(SUBSTITUTE('01_Corrupted_General_Ledger'!F13, "$", ""), " ", ""))), 0) -> 210 | G13: =E13*F13 -> 0 | H13: =IF(OR(ISERROR('01_Corrupted_General_Ledger'!G13), '01_Corrupted_General_Ledger'!D13="VEND-999"), "REPAIRED", "VERIFIED CLEAN") -> REPAIRED
... A101: ='01_Corrupted_General_Ledger'!A101 -> TXN-1100 | B101: ='01_Corrupted_General_Ledger'!B101 -> 46072 | C101: ='01_Corrupted_General_Ledger'!C101 -> 6003-SUPPLY | D101: =IF(OR('01_Corrupted_General_Ledger'!D101="VEND-999", '01_Corrupted_General_Ledger'!D101="#N/A", ISBLANK('01_Corrupted_General_Ledger'!D101)), "VEND-DEFAULT", '01_Corrupted_General_Ledger'!D101) -> VEND-900 | E101: =IFERROR(VALUE(TRIM('01_Corrupted_General_Ledger'!E101)), 1) -> 175 | F101: =IFERROR(VALUE(TRIM(SUBSTITUTE(SUBSTITUTE('01_Corrupted_General_Ledger'!F101, "$", ""), " ", ""))), 0) -> 92 | G101: =E101*F101 -> 16100 | H101: =IF(OR(ISERROR('01_Corrupted_General_Ledger'!G101), '01_Corrupted_General_Ledger'!D101="VEND-999"), "REPAIRED", "VERIFIED CLEAN") -> VERIFIED CLEAN

Sheet 03_Reconciliation_Matrix
A1: Txn_ID | B1: Repaired_Extended_Cost | C1: Target_Subledger_Balance | D1: Absolute_Variance | E1: Tolerance_Threshold | F1: Reconciliation_Status
A2: ='02_Formula_Repair_Engine'!A2 -> TXN-1001 | B2: ='02_Formula_Repair_Engine'!G2 -> 6750 | C2: ='01_Corrupted_General_Ledger'!H2 -> 6750 | D2: =ABS(B2-C2) -> 0 | E2: 0.05 | F2: =IF(D2<=E2, "MATCHED", "VARIANCE DETECTED") -> MATCHED
A3: ='02_Formula_Repair_Engine'!A3 -> TXN-1002 | B3: ='02_Formula_Repair_Engine'!G3 -> 0 | C3: ='01_Corrupted_General_Ledger'!H3 -> 3200 | D3: =ABS(B3-C3) -> 3200 | E3: 0.05 | F3: =IF(D3<=E3, "MATCHED", "VARIANCE DETECTED") -> VARIANCE DETECTED
A4: ='02_Formula_Repair_Engine'!A4 -> TXN-1003 | B4: ='02_Formula_Repair_Engine'!G4 -> 0 | C4: ='01_Corrupted_General_Ledger'!H4 -> 0 | D4: =ABS(B4-C4) -> 0 | E4: 0.05 | F4: =IF(D4<=E4, "MATCHED", "VARIANCE DETECTED") -> MATCHED
A5: ='02_Formula_Repair_Engine'!A5 -> TXN-1004 | B5: ='02_Formula_Repair_Engine'!G5 -> 3100 | C5: ='01_Corrupted_General_Ledger'!H5 -> 3100 | D5: =ABS(B5-C5) -> 0 | E5: 0.05 | F5: =IF(D5<=E5, "MATCHED", "VARIANCE DETECTED") -> MATCHED
A6: ='02_Formula_Repair_Engine'!A6 -> TXN-1005 | B6: ='02_Formula_Repair_Engine'!G6 -> 15500 | C6: ='01_Corrupted_General_Ledger'!H6 -> 15500 | D6: =ABS(B6-C6) -> 0 | E6: 0.05 | F6: =IF(D6<=E6, "MATCHED", "VARIANCE DETECTED") -> MATCHED
A7: ='02_Formula_Repair_Engine'!A7 -> TXN-1006 | B7: ='02_Formula_Repair_Engine'!G7 -> 75 | C7: ='01_Corrupted_General_Ledger'!H7 -> 1875 | D7: =ABS(B7-C7) -> 1800 | E7: 0.05 | F7: =IF(D7<=E7, "MATCHED", "VARIANCE DETECTED") -> VARIANCE DETECTED
A8: ='02_Formula_Repair_Engine'!A8 -> TXN-1007 | B8: ='02_Formula_Repair_Engine'!G8 -> 11400 | C8: ='01_Corrupted_General_Ledger'!H8 -> 11400 | D8: =ABS(B8-C8) -> 0 | E8: 0.05 | F8: =IF(D8<=E8, "MATCHED", "VARIANCE DETECTED") -> MATCHED
A9: ='02_Formula_Repair_Engine'!A9 -> TXN-1008 | B9: ='02_Formula_Repair_Engine'!G9 -> 0 | C9: ='01_Corrupted_General_Ledger'!H9 -> 0 | D9: =ABS(B9-C9) -> 0 | E9: 0.05 | F9: =IF(D9<=E9, "MATCHED", "VARIANCE DETECTED") -> MATCHED
A10: ='02_Formula_Repair_Engine'!A10 -> TXN-1009 | B10: ='02_Formula_Repair_Engine'!G10 -> 0 | C10: ='01_Corrupted_General_Ledger'!H10 -> 1800 | D10: =ABS(B10-C10) -> 1800 | E10: 0.05 | F10: =IF(D10<=E10, "MATCHED", "VARIANCE DETECTED") -> VARIANCE DETECTED
A11: ='02_Formula_Repair_Engine'!A11 -> TXN-1010 | B11: ='02_Formula_Repair_Engine'!G11 -> 6250 | C11: ='01_Corrupted_General_Ledger'!H11 -> 6250 | D11: =ABS(B11-C11) -> 0 | E11: 0.05 | F11: =IF(D11<=E11, "MATCHED", "VARIANCE DETECTED") -> MATCHED
A12: ='02_Formula_Repair_Engine'!A12 -> TXN-1011 | B12: ='02_Formula_Repair_Engine'!G12 -> 15400 | C12: ='01_Corrupted_General_Ledger'!H12 -> 15400 | D12: =ABS(B12-C12) -> 0 | E12: 0.05 | F12: =IF(D12<=E12, "MATCHED", "VARIANCE DETECTED") -> MATCHED
A13: ='02_Formula_Repair_Engine'!A13 -> TXN-1012 | B13: ='02_Formula_Repair_Engine'!G13 -> 0 | C13: ='01_Corrupted_General_Ledger'!H13 -> 0 | D13: =ABS(B13-C13) -> 0 | E13: 0.05 | F13: =IF(D13<=E13, "MATCHED", "VARIANCE DETECTED") -> MATCHED
... A101: ='02_Formula_Repair_Engine'!A101 -> TXN-1100 | B101: ='02_Formula_Repair_Engine'!G101 -> 16100 | C101: ='01_Corrupted_General_Ledger'!H101 -> 16100 | D101: =ABS(B101-C101) -> 0 | E101: 0.05 | F101: =IF(D101<=E101, "MATCHED", "VARIANCE DETECTED") -> MATCHED

Sheet 04_Audit_Executive_Console
B5: Total Transactions Audited | D5: Errors Trapped & Repaired | F5: Reconciliation Variances | H5: System Health Score
B6: =COUNTA('01_Corrupted_General_Ledger'!A2:A101) -> 100 | D6: =COUNTIF('02_Formula_Repair_Engine'!H2:H101, "REPAIRED") -> 44 | F6: =COUNTIF('03_Reconciliation_Matrix'!F2:F101, "VARIANCE DETECTED") -> 28 | H6: =(1 - (F6 / B6)) -> 0.72
